amplify/__init__.py
amplify/src/__init__.py
amplify/src/amplify.py
amplify/src/data_classes.py
amplify/src/flex_calculation.py
amplify/tests/__init__.py
amplify/tests/unit_tests/__init__.py
amplify/tests/unit_tests/general/evaluate_execution_time.py
amplify/tests/unit_tests/general/execution_time.csv
amplify/tests/unit_tests/general/results_execution_time.txt
amplify/tests/unit_tests/general/test_ppr_detection.py
amplify/tests/unit_tests/general/test_total_flex_calculation.py
amplify/tests/unit_tests/mpos/full_result_test_accept_long_trades_scenarios.txt
amplify/tests/unit_tests/mpos/test_accept_long_trades_scenarios.py
amplify/tests/unit_tests/mpos/test_accept_short_cap-mpos_scenarios.py
amplify/tests/unit_tests/mpos/test_accept_short_trades_scenarios.py
amplify/tests/unit_tests/util/aggregate_flexibility.py
amplify/tests/unit_tests/util/analyze_single_scenario.py
amplify/tests/unit_tests/util/generate_capacity_trades.py
amplify/tests/unit_tests/util/generate_trades.py
amplify/tests/unit_tests/util/place_mpos.py
amplify_model-0.1.2.dist-info/LICENSE
amplify_model-0.1.2.dist-info/METADATA
amplify_model-0.1.2.dist-info/WHEEL
amplify_model-0.1.2.dist-info/RECORD
