Metadata-Version: 2.1
Name: amplify-model
Version: 0.1.2
Summary: Amplify (abstract multi-purpose-limited flexibility) is a model for operational flexibility remaining after a primary application is fullfilled by distributed energy resources.
License: Apache-2.0
Author: Paul Hendrik Tiemann
Author-email: paul.hendrik.tiemann@uni-oldenburg.de
Requires-Python: >=3.8,<4.0
Classifier: License :: OSI Approved :: Apache Software License
Classifier: Programming Language :: Python :: 3
Classifier: Programming Language :: Python :: 3.8
Classifier: Programming Language :: Python :: 3.9
Classifier: Programming Language :: Python :: 3.10
Classifier: Programming Language :: Python :: 3.11
Classifier: Programming Language :: Python :: 3.12
Requires-Dist: pytest (>=7.1.2,<8.0.0)
